{"result": {"folders": ["lecture9", "工具使用", "2017"], "nr": 1016, "data": {"embed_links": []}, "created": "2017-03-21T02:18:57Z", "bucket_order": 3, "no_answer_followup": 0, "change_log": [{"anon": "stud", "data": "j0iwvq8qwobt6", "type": "create", "when": "2017-03-21T02:18:57Z", "uid_a": "a_0"}, {"anon": "no", "uid": "hdjonbiyfs62ie", "data": "j0iyhuagfee5w1", "to": "j0iwvq8l14ut5", "type": "i_answer", "when": "2017-03-21T03:04:08Z"}, {"anon": "no", "uid": "ie7xy0nh1811ls", "data": "j0iymsbgmdl27b", "type": "update", "when": "2017-03-21T03:07:59Z"}, {"anon": "no", "uid": "ie7xy0nh1811ls", "data": "j0j3y6rnymn1f4", "type": "update", "when": "2017-03-21T05:36:49Z"}, {"anon": "no", "uid": "ie7xy0nh1811ls", "data": "j0sv1sf2m8sk6", "to": "j0iwvq8l14ut5", "type": "s_answer", "when": "2017-03-28T01:25:22Z"}, {"anon": "no", "uid": "hdjonbiyfs62ie", "to": "j0iwvq8l14ut5", "type": "followup", "when": "2017-03-28T02:43:43Z"}, {"anon": "no", "uid": "hdjonbiyfs62ie", "data": "j7t7niequkv5ux", "type": "update", "when": "2017-09-20T15:56:07Z"}], "bucket_name": "Today", "history": [{"anon": "no", "uid": "hdjonbiyfs62ie", "subject": "搭了一个墙内访问piazza的中转站", "created": "2017-09-20T15:56:07Z", "content": "<p><a target=\"_blank\">https://piazza.jinzihao.me</a></p>\n<p>&#xff08;我自己是完全没遇到过访问不了piazza的问题&#xff0c;也不需要翻墙访问&#xff0c;所以这个好不好用我自己没法测试&#xff0c;先试试看吧…&#xff09;</p>"}, {"anon": "no", "uid": "ie7xy0nh1811ls", "subject": "搭了一个墙内访问piazza的中转站", "created": "2017-03-21T05:36:49Z", "content": "<p><a target=\"_blank\">https://piazza.jinzihao.me</a></p>\n<p>&#xff08;我自己是完全没遇到过访问不了piazza的问题&#xff0c;也不需要翻墙访问&#xff0c;所以这个好不好用我自己没法测试&#xff0c;先试试看吧…&#xff09;</p>"}, {"anon": "no", "uid": "ie7xy0nh1811ls", "subject": "搭了一个墙内访问piazza的中转站", "created": "2017-03-21T03:07:59Z", "content": "<p>https://piazza.jinzihao.me</p>\n<p>&#xff08;我自己是完全没遇到过访问不了piazza的问题&#xff0c;也不需要翻墙访问&#xff0c;所以这个好不好用我自己没法测试&#xff0c;先试试看吧…&#xff09;</p>"}, {"anon": "stud", "uid_a": "a_0", "subject": "搭了一个墙内访问piazza的中转站", "created": "2017-03-21T02:18:57Z", "content": "<p><a href=\"https://piazza.jinzihao.me\">https://piazza.jinzihao.me</a></p>\n<p>&#xff08;我自己是完全没遇到过访问不了piazza的问题&#xff0c;也不需要翻墙访问&#xff0c;所以这个好不好用我自己没法测试&#xff0c;先试试看吧…&#xff09;</p>"}], "type": "question", "tags": ["2017", "lecture9", "student", "工具使用"], "tag_good": [], "unique_views": 146, "children": [{"folders": [], "data": {"embed_links": []}, "children": [], "created": "2017-03-21T03:04:08Z", "bucket_order": 3, "tag_endorse": [], "bucket_name": "Today", "id": "j0iyhuaefzt5w0", "history": [{"anon": "no", "uid": "hdjonbiyfs62ie", "subject": "", "created": "2017-03-21T03:04:08Z", "content": "<p>谢谢。我让其他同学试一下你的链接。</p>"}], "type": "i_answer", "tag_endorse_arr": [], "config": {}, "is_tag_endorse": false}, {"folders": [], "data": {"embed_links": []}, "children": [], "created": "2017-03-28T01:25:22Z", "bucket_order": 3, "tag_endorse": [], "bucket_name": "Today", "id": "j0sv1sf15qgk5", "history": [{"anon": "no", "uid": "ie7xy0nh1811ls", "subject": "", "created": "2017-03-28T01:25:22Z", "content": "<p>大概是需要先执行&#xff1a;</p>\n<pre>sudo a2enmod proxy<br />sudo a2enmod proxy_http<br />sudo a2enmod proxy_connect</pre>\n<p>然后将 http://lab.jinzihao.me/files/piazza.jinzihao.me.conf 配置文件复制到/etc/apache2/sites-enabled/就好了~</p>\n<p></p>"}], "type": "s_answer", "tag_endorse_arr": [], "config": {}, "is_tag_endorse": false}, {"anon": "no", "folders": [], "data": {"embed_links": null}, "no_upvotes": 0, "subject": "<p>谢谢&#xff01;</p>", "created": "2017-03-28T02:43:43Z", "bucket_order": 157, "bucket_name": "Week 3/26 - 4/1", "type": "followup", "tag_good": [], "uid": "hdjonbiyfs62ie", "children": [], "tag_good_arr": [], "no_answer": 0, "id": "j0sxujzp8qo2t8", "updated": "2017-03-28T02:43:43Z", "config": {}}], "tag_good_arr": [], "no_answer": 0, "id": "j0iwvq8l14ut5", "config": {}, "status": "active", "drafts": null, "request_instructor": 0, "request_instructor_me": false, "bookmarked": 2, "num_favorites": 0, "my_favorite": false, "is_bookmarked": false, "is_tag_good": false, "q_edits": [], "i_edits": [], "s_edits": [], "t": 1643168983120, "default_anonymity": "no"}, "error": null, "aid": "kyv0dxsgw6a3d"}