{"result": {"folders": ["lecture10", "lecture11", "2017"], "nr": 1025, "data": {"embed_links": []}, "created": "2017-03-28T12:00:59Z", "bucket_order": 3, "no_answer_followup": 0, "change_log": [{"anon": "no", "uid": "hcrrjuyequh4bt", "data": "j0thr7cdq8s21i", "type": "create", "when": "2017-03-28T12:00:59Z"}, {"anon": "no", "uid": "hdjonbiyfs62ie", "data": "j0tnsoa0ma859x", "type": "update", "when": "2017-03-28T14:50:05Z"}], "bucket_name": "Today", "history": [{"anon": "no", "uid": "hdjonbiyfs62ie", "subject": "lec10&amp;11的思考与练习", "created": "2017-03-28T14:50:05Z", "content": "<p>供有时间的同学作为课后思考和练习</p>\n<p></p>\n<p>1 以lab3为例&#xff0c;说明虚拟页与磁盘后备页面的对应关系是什么&#xff1f;<br />2 以lab4为例&#xff0c;理解保存现场和恢复现场&#xff1a; lab4/kern/process/switch.S <br />3 理解进程的各种状态和各种状态间的转换的起因。<br />4 由于何种原因&#xff0c;可出现进程的何种状态转到退出状态&#xff1f;<br />5 请设计一个简化的进程管理子系统&#xff0c;可以管理并调度如下简化进程.给出了参考代码&#xff08;https://github.com/chyyuu/ucore_lab/blob/master/related_info/lab4/process-concept-homework.py&#xff09;&#xff0c;请理解代码&#xff0c;并完成&#xff02;YOUR CODE&#34;部分的内容。<br />6 请了解实际操作系统Linux的各种状态和各种状态间的转换的起因。<br />7 请了解实际操作系统Linux的进程控制块PCB数据结构 task_struct</p>"}, {"anon": "no", "uid": "hcrrjuyequh4bt", "subject": "lec10&amp;11的思考与练习", "created": "2017-03-28T12:00:59Z", "content": "<p>供有时间的同学作为课后思考和练习</p>\n<p></p>\n<p>1 以lab3为例&#xff0c;说明虚拟页与磁盘后备页面的对应关系是什么&#xff1f;<br />2 以lab4为例&#xff0c;理解保存现场和恢复现场&#xff1a; lab4/kern/process/switch.S <br />3 理解进程的各种状态和各种状态间的转换的起因。<br />4 由于何种原因&#xff0c;可出现进程的何种状态转到退出状态&#xff1f;<br />5 请设计一个简化的进程管理子系统&#xff0c;可以管理并调度如下简化进程.给出了参考代码&#xff08;https://github.com/chyyuu/ucore_lab/blob/master/related_info/lab4/process-concept-homework.py&#xff09;&#xff0c;请理解代码&#xff0c;并完成&#xff02;YOUR CODE&#34;部分的内容。<br />6 请了解实际操作系统Linux的各种状态和各种状态间的转换的起因。<br />7 请了解实际操作系统Linux的进程控制块PCB数据结构 task_struct </p>"}], "type": "note", "tags": ["2017", "instructor-note", "lecture10", "lecture11"], "tag_good": [], "unique_views": 122, "children": [], "tag_good_arr": [], "id": "j0thr7cbwbw21h", "config": {}, "status": "active", "drafts": null, "request_instructor": 0, "request_instructor_me": false, "bookmarked": 5, "num_favorites": 2, "my_favorite": false, "is_bookmarked": false, "is_tag_good": false, "q_edits": [], "i_edits": [], "s_edits": [], "t": 1643168995062, "default_anonymity": "no"}, "error": null, "aid": "kyv0e706acp1lc"}