{"result": {"folders": ["lecture1", "lecture2"], "nr": 1139, "data": {"embed_links": []}, "created": "2018-03-04T16:00:45Z", "bucket_order": 3, "no_answer_followup": 0, "change_log": [{"anon": "no", "uid": "isvte2o93ju2dt", "data": "jeczh11qt434rw", "type": "create", "when": "2018-03-04T16:00:45Z"}], "bucket_name": "Today", "history": [{"anon": "no", "uid": "isvte2o93ju2dt", "subject": "第一周练习批改情况", "created": "2018-03-04T16:00:45Z", "content": "<p>第一周的两次作业已经批改完毕&#xff0c;对于练习分数有疑问的同学请在<strong>3月6日23:59</strong>前回复本贴&#xff0c;说明自己的学号和问题以方便助教修正。</p>\n<p></p>\n<p>另外&#xff0c;关于练习批改有几点需要说明&#xff1a;</p>\n<ol><li>练习<strong>不计入成绩</strong>&#xff0c;但会<strong>在考试中体现</strong></li><li>对于每次练习&#xff0c;助教只会选取 20 名同学批改</li><li>我们会尽量挑选不同的同学&#xff0c;保证每个提交了作业的同学都有机会被改到</li></ol>\n<p>课程练习的答案位于 os_course_exercises 的 <a href=\"https://github.com/chyyuu/os_course_exercises/tree/2018spring-answer\" target=\"_blank\">2018spring-answer</a> 分支&#xff0c;这些答案基本是根据同学们提交的答案和 <a href=\"https://github.com/chyyuu/os_course_exercises/tree/master\" target=\"_blank\">master</a> 分支中原有的答案整合而成的&#xff0c;因此难免有疏漏&#xff0c;欢迎同学们指正。另外&#xff0c;大部分简答题没有绝对标准的答案&#xff0c;大家理解清楚相应的知识点即可。</p>\n<p></p>\n<p>在批改过程中&#xff0c;我发现有不少同学直接照搬答案。我不反对看答案&#xff0c;但是原始答案比较粗糙&#xff0c;同学们也要有自己的判断。</p>"}], "type": "note", "tags": ["instructor-note", "lecture1", "lecture2"], "tag_good": [], "unique_views": 217, "children": [], "tag_good_arr": [], "id": "jeczh10fv2v4rv", "config": {}, "status": "active", "drafts": null, "request_instructor": 0, "request_instructor_me": false, "bookmarked": 1, "num_favorites": 1, "my_favorite": false, "is_bookmarked": false, "is_tag_good": false, "q_edits": [], "i_edits": [], "s_edits": [], "t": 1643169210103, "default_anonymity": "no"}, "error": null, "aid": "kyv0isxju4q6wg"}