{"result": {"folders": ["lab1"], "nr": 115, "data": {"embed_links": []}, "created": "2015-03-15T22:42:01Z", "bucket_order": 3, "no_answer_followup": 0, "change_log": [{"uid": "hwfmxxld7w611e", "anon": "no", "when": "2015-03-15T22:42:01Z", "data": "i7b11t1mzub254", "type": "create"}, {"to": "i7b11t1heqa252", "uid": "hdjoucuyb836fq", "anon": "no", "when": "2015-03-16T00:24:36Z", "data": "i7b4pq11thgiq", "type": "i_answer"}, {"uid": "hcrrjuyequh4bt", "anon": "no", "when": "2015-03-16T02:34:38Z", "data": "i7b9cy6bt2y1e6", "type": "i_answer_update"}, {"uid": "hdjoucuyb836fq", "anon": "no", "when": "2015-03-16T02:37:30Z", "data": "i7b9gmj1ri42nu", "type": "i_answer_update"}, {"to": "i7b11t1heqa252", "uid": "hwfmxxld7w611e", "anon": "no", "when": "2015-03-16T07:09:33Z", "type": "followup"}, {"uid": "hdjoucuyb836fq", "anon": "no", "when": "2015-03-16T10:47:36Z", "data": "i7bqyweaz2c1mc", "type": "i_answer_update"}, {"to": "i7b11t1heqa252", "uid": "hcrrjuyequh4bt", "anon": "no", "when": "2015-03-16T15:41:16Z", "type": "feedback"}], "bucket_name": "Today", "history": [{"anon": "no", "uid": "hwfmxxld7w611e", "subject": "关于保护模式下逻辑地址空间寻址", "created": "2015-03-15T22:42:01Z", "content": "<p>只有在保护模式下,80386的全部32根地址线有效,可寻址高达4G字节的线性地址空间和物理地址空间,可访问64TB(有<br />2^14个段,每个段最大空间为2^32字节)的逻辑地址空间</p>\n<p>为什么是2^14个段&#xff1f;</p>"}], "type": "question", "tags": ["lab1", "student"], "tag_good": [], "unique_views": 134, "children": [{"folders": [], "data": {"embed_links": []}, "children": [], "created": "2015-03-16T00:24:36Z", "bucket_order": 3, "tag_endorse": [], "bucket_name": "Today", "id": "i7b4pq0ylxpio", "history": [{"anon": "no", "uid": "hdjoucuyb836fq", "subject": "", "created": "2015-03-16T10:47:36Z", "content": "<p>保护模式下&#xff0c;段表包括GDT&#xff08;Global Descriptor Table&#xff09;和LDT&#xff08;Local Descriptor Table&#xff09;两张&#xff0c;每一张段表可以包含8192 (2^13)个描述符[1]&#xff0c;因而最多可以同时存在2 * 2^13 = 2^14个段。<br /></p>\n<p></p>\n<p>虽然保护模式下可以有这么多段&#xff0c;逻辑地址空间看起来很大&#xff0c;但实际上段并不能扩展物理地址空间&#xff0c;所谓的64TB逻辑地址空间&#xff0c;很大程度上是相互重叠的&#xff0c;在32位模式下&#xff0c;真正的物理空间仍然只有2^32字节那么大。</p>\n<p></p>\n<p>Reference</p>\n<p>[1] 3.5.1 Segment Descriptor Tables, Intel® 64 and IA-32 Architectures Software Developer’s Manual</p>"}, {"anon": "no", "uid": "hdjoucuyb836fq", "subject": "", "created": "2015-03-16T02:37:30Z", "content": "<p>这段话的上下文是在哪一章节&#xff1f; </p>\n<p>请给出网址</p>"}, {"anon": "no", "uid": "hcrrjuyequh4bt", "subject": "", "created": "2015-03-16T02:34:38Z", "content": "<p>这段话的上下文是在哪一章节&#xff1f; </p>\n<p>请给出网址&#xff01;</p>"}, {"anon": "no", "uid": "hdjoucuyb836fq", "subject": "", "created": "2015-03-16T00:24:36Z", "content": "<p>这段话的上下文是在哪一章节&#xff1f;</p>"}], "type": "i_answer", "tag_endorse_arr": [], "config": {}, "is_tag_endorse": false}, {"anon": "no", "folders": [], "data": {"embed_links": null}, "no_upvotes": 0, "subject": "<p><a href=\"http://objectkuan.gitbooks.io/ucore-docs/content/lab1/lab1_3_2_1_protection_mode.html\">http://objectkuan.gitbooks.io/ucore-docs/content/lab1/lab1_3_2_1_protection_mode.html</a></p>\n<p>实验指导书2.3.2.1保护模式与分段机制里面的内容</p>", "created": "2015-03-16T07:09:33Z", "bucket_order": 280, "bucket_name": "Week 3/15 - 3/21", "type": "followup", "tag_good": [], "uid": "hwfmxxld7w611e", "children": [{"anon": "no", "folders": [], "data": {"embed_links": null}, "subject": "<p>多谢&#xff01;以把上述信息更新到 <a href=\"http://objectkuan.gitbooks.io/ucore-docs/content/lab1/lab1_3_2_1_protection_mode.html\" target=\"_blank\">http://objectkuan.gitbooks.io/ucore-docs/content/lab1/lab1_3_2_1_protection_mode.html</a></p>\n<p>如果有不清楚的&#xff0c;请多提问。我们会及时改进&#xff01;</p>", "created": "2015-03-16T15:41:16Z", "bucket_order": 280, "bucket_name": "Week 3/15 - 3/21", "type": "feedback", "tag_good": [], "uid": "hcrrjuyequh4bt", "children": [], "tag_good_arr": [], "id": "i7c1gk4vleq63h", "updated": "2015-03-16T15:41:16Z", "config": {}}], "tag_good_arr": [], "no_answer": 0, "id": "i7bj6hrfl2h19o", "updated": "2015-03-16T07:09:33Z", "config": {}}], "tag_good_arr": [], "no_answer": 0, "id": "i7b11t1heqa252", "config": {}, "status": "active", "drafts": null, "request_instructor": 0, "request_instructor_me": false, "bookmarked": 5, "num_favorites": 1, "my_favorite": false, "is_bookmarked": false, "is_tag_good": false, "q_edits": [], "i_edits": [], "s_edits": [], "t": 1643167336169, "default_anonymity": "no"}, "error": null, "aid": "kyuzemztab95nc"}