{"result": {"folders": ["文档纠错", "2018"], "nr": 1155, "data": {"embed_links": []}, "created": "2018-03-14T12:01:15Z", "bucket_order": 3, "no_answer_followup": 0, "change_log": [{"anon": "no", "uid": "je2ib2uxxq069j", "data": "jer1bj8gj5n4gq", "type": "create", "when": "2018-03-14T12:01:15Z"}, {"anon": "no", "uid": "je2ib2uxxq069j", "data": "jer1d0thrg34yy", "type": "update", "when": "2018-03-14T12:02:24Z"}, {"anon": "no", "uid": "hdjonbiyfs62ie", "data": "jer8ztjysce7oo", "to": "jer1bj8e4kt4gp", "type": "i_answer", "when": "2018-03-14T15:36:05Z"}], "bucket_name": "Today", "history": [{"anon": "no", "uid": "je2ib2uxxq069j", "subject": "&#34;实验结果提交约定&#34;中仓库路径应更正", "created": "2018-03-14T12:02:24Z", "content": "<p>http://os.cs.tsinghua.edu.cn/oscourse/OS2018spring/log中“20180309-实验结果提交约定”一节中&#xff0c;代码仓库路径应更正为<span style=\"font-family:&#34;Consolas&#34;\">http://github.com/oscourse-tsinghua/os2018-[githubid]/tree/master/labcodes/lab[x]</span></p>"}, {"anon": "no", "uid": "je2ib2uxxq069j", "subject": "&#34;实验结果提交约定&#34;中仓库路径更正", "created": "2018-03-14T12:01:15Z", "content": "<p>http://os.cs.tsinghua.edu.cn/oscourse/OS2018spring/log中“20180309-实验结果提交约定”一节中&#xff0c;代码仓库路径应更正为<span style=\"font-family:&#34;Consolas&#34;\">http://github.com/oscourse-tsinghua/os2018-[githubid]/tree/master/labcodes/lab[x]</span></p>"}], "type": "question", "tags": ["2018", "student", "文档纠错"], "tag_good": [], "unique_views": 82, "children": [{"folders": [], "data": {"embed_links": []}, "children": [], "created": "2018-03-14T15:36:05Z", "bucket_order": 3, "tag_endorse": [], "bucket_name": "Today", "id": "jer8ztjtpjb7on", "history": [{"anon": "no", "uid": "hdjonbiyfs62ie", "subject": "", "created": "2018-03-14T15:36:05Z", "content": "<p>谢谢&#xff01;已更正。</p>"}], "type": "i_answer", "tag_endorse_arr": [], "config": {}, "is_tag_endorse": false}], "tag_good_arr": [], "no_answer": 0, "id": "jer1bj8e4kt4gp", "config": {}, "status": "active", "drafts": null, "request_instructor": 0, "request_instructor_me": false, "bookmarked": 2, "num_favorites": 0, "my_favorite": false, "is_bookmarked": false, "is_tag_good": false, "q_edits": [], "i_edits": [], "s_edits": [], "t": 1643169262464, "default_anonymity": "no"}, "error": null, "aid": "kyv0jxc0go03kc"}