{"result": {"folders": ["2019"], "nr": 1356, "data": {"embed_links": []}, "created": "2019-10-24T04:26:29Z", "bucket_order": 3, "no_answer_followup": 0, "change_log": [{"anon": "no", "uid": "jxx6plxsq6l4us", "data": "k247fg4ed011hh", "type": "create", "when": "2019-10-24T04:26:29Z"}, {"anon": "no", "uid": "hdjonbiyfs62ie", "to": "k247fg4cled1hg", "type": "followup", "when": "2019-10-30T03:19:10Z"}], "bucket_name": "Today", "history": [{"anon": "no", "uid": "jxx6plxsq6l4us", "subject": "LRU不会belady 的证明", "created": "2019-10-24T04:26:29Z", "content": "看到之前学长的证明好长&#xff0c;其实可以简单点不用数学归纳。<img src=\"/img/1356-aa826bfc0a9429ae.jpg\" />"}], "type": "note", "tags": ["2019", "student"], "tag_good": [], "unique_views": 137, "children": [{"anon": "no", "folders": [], "data": {"embed_links": null}, "no_upvotes": 0, "subject": "<p>你的这个描述仍然是归纳法&#xff0c;而且描述比较简略。与已有的证明是一致的。</p>", "created": "2019-10-30T03:19:10Z", "bucket_order": 22, "bucket_name": "Week 10/27 - 11/2", "type": "followup", "tag_good": [], "uid": "hdjonbiyfs62ie", "children": [], "tag_good_arr": [], "no_answer": 0, "id": "k2cpo013hmw38e", "updated": "2019-10-30T03:19:10Z", "config": {}}], "tag_good_arr": [], "id": "k247fg4cled1hg", "config": {}, "status": "active", "drafts": null, "request_instructor": 0, "request_instructor_me": false, "bookmarked": 3, "num_favorites": 1, "my_favorite": false, "is_bookmarked": false, "is_tag_good": false, "q_edits": [], "i_edits": [], "s_edits": [], "t": 1643169819115, "default_anonymity": "no"}, "error": null, "aid": "kyv0vuuj1sd6b0"}