{"result": {"folders": ["lab2"], "nr": 1494, "data": {"embed_links": []}, "created": "2020-09-09T09:00:27Z", "bucket_order": 3, "no_answer_followup": 0, "change_log": [{"anon": "no", "uid": "k42oyz6pieh1nk", "data": "kev5k7m9mc15k", "v": "all", "type": "create", "when": "2020-09-09T09:00:27Z"}], "bucket_name": "Today", "history": [{"anon": "no", "uid": "k42oyz6pieh1nk", "subject": "为什么我的gdb调试信息是错的&#xff1f;", "created": "2020-09-09T09:00:27Z", "content": "<p>这是第一张图&#xff0c;我把pmm.c的第195行设置为断点&#xff0c;然后用gdb打印maxpa是一个奇奇怪怪的数&#xff0c;但是地址确是正确的。</p>\n<p><img src=\"/img/1494-6784824c04985417.png\" alt=\"\" /></p>\n<p>第二章图是打印信息&#xff0c;和gdb不太一样。<img src=\"/img/1494-6784824c04985417.png\" width=\"1000\" height=\"175\" alt=\"\" /></p>"}], "type": "question", "tags": ["lab2", "student", "unanswered"], "tag_good": [], "unique_views": 121, "children": [], "tag_good_arr": [], "no_answer": 1, "id": "kev5k7m7d815j", "config": {"seen": {"122": 6, "760": 8, "102": 4, "1137": 0, "400": 2, "554": 1, "1267": 9, "1210": 7, "547": 5, "1192": 3}}, "status": "active", "drafts": null, "request_instructor": 0, "request_instructor_me": false, "bookmarked": 1, "num_favorites": 0, "my_favorite": false, "is_bookmarked": false, "is_tag_good": false, "q_edits": [], "i_edits": [], "s_edits": [], "t": 1643170201447, "default_anonymity": "no"}, "error": null, "aid": "kyv141uvsge2jl"}