{"result": {"folders": ["other"], "nr": 501, "data": {"embed_links": []}, "created": "2015-07-27T02:10:25Z", "bucket_order": 3, "no_answer_followup": 0, "change_log": [{"uid": "hdjonbiyfs62ie", "anon": "no", "when": "2015-07-27T02:10:25Z", "data": "icla23czszz1hu", "type": "create"}, {"uid": "hdjonbiyfs62ie", "anon": "no", "when": "2015-07-27T02:11:26Z", "data": "icla3emgilc2p0", "type": "update"}, {"to": "icla23cwgp91ht", "uid": "i8iq189u68z35u", "anon": "no", "when": "2015-07-28T17:33:21Z", "type": "followup"}, {"to": "icla23cwgp91ht", "uid": "hdjonbiyfs62ie", "anon": "no", "when": "2015-07-29T03:23:01Z", "type": "feedback"}], "bucket_name": "Today", "history": [{"anon": "no", "uid": "hdjonbiyfs62ie", "subject": "关于学堂在线“操作系统”课程证书的问题", "created": "2015-07-27T02:11:26Z", "content": "<p></p><p>在 2015年7月27日&#xff0c;上午10:04&#xff0c;xyong &lt;xyong&#64;mail.tsinghua.edu.cn&gt; 写道&#xff1a;</p>\n<p></p>\n<p>是证书还没发呢 等等就可以看到了。</p>\n<p></p>\n<p>--向勇</p>\n<p></p>\n<p>在 2015年7月25日&#xff0c;上午8:49&#xff0c;天琊何处 &lt;<a href=\"mailto:923844041&#64;qq.com\">923844041&#64;qq.com</a>&gt; 写道&#xff1a;</p>\n<p></p>\n<p>老师您好&#xff0c;我是学堂在线操作系统课程的一名学生&#xff0c;我的ID是xxx&#xff0c;我的汇总成绩是xx分&#xff0c;但是课程没有出现申请证书的页面。</p>\n<p>一般获得证书可以可以在主页面选择下载证书&#xff1a;&#xff08;课程已经结束&#xff0c;下载证书&#xff09;</p>\n<p><img src=\"/img/501-12d523d9e064172f.jpg\" /></p>\n<p>但是操作系统这门课我的结果是这样的&#xff1a;&#xff08;最终课程细节目前正在被封闭&#xff0c;您很快就能看到最终名次&#xff09;</p>\n<p></p>\n<p><img src=\"/img/501-38f2cbc743f4197f.jpg\" /></p>\n<p>希望老师能帮我解决一下这个问题&#xff0c;谢谢</p>"}, {"anon": "no", "uid": "hdjonbiyfs62ie", "subject": "关于学堂在线“操作系统”课程证书的问题", "created": "2015-07-27T02:10:25Z", "content": "<p></p><p>在 2015年7月25日&#xff0c;上午8:49&#xff0c;天琊何处 &lt;<a href=\"mailto:923844041&#64;qq.com\">923844041&#64;qq.com</a>&gt; 写道&#xff1a;</p>\n<p></p>\n<p>老师您好&#xff0c;我是学堂在线操作系统课程的一名学生&#xff0c;我的ID是xxx&#xff0c;我的汇总成绩是xx分&#xff0c;但是课程没有出现申请证书的页面。</p>\n<p>一般获得证书可以可以在主页面选择下载证书&#xff1a;&#xff08;课程已经结束&#xff0c;下载证书&#xff09;</p>\n<p><img src=\"/img/501-12d523d9e064172f.jpg\" /></p>\n<p>但是操作系统这门课我的结果是这样的&#xff1a;&#xff08;最终课程细节目前正在被封闭&#xff0c;您很快就能看到最终名次&#xff09;</p>\n<p></p>\n<p><img src=\"/img/501-38f2cbc743f4197f.jpg\" /></p>\n<p>希望老师能帮我解决一下这个问题&#xff0c;谢谢</p>"}], "type": "note", "tags": ["instructor-note", "other"], "tag_good": [], "unique_views": 61, "children": [{"anon": "no", "folders": [], "data": {"embed_links": null}, "no_upvotes": 0, "subject": "<p>我在想&#xff0c;老师是不是不来看论坛了。。。。。</p>", "created": "2015-07-28T17:33:21Z", "bucket_order": 247, "bucket_name": "Week 7/26 - 8/1", "type": "followup", "tag_good": [], "uid": "i8iq189u68z35u", "children": [{"anon": "no", "folders": [], "data": {"embed_links": null}, "subject": "<p>现在是暑假期间&#xff0c;老师回复同学问题的响应时间会比平时长一些&#xff0c;但仍然还是会回复的。有任何与操作系统课相关的技术问题&#xff0c;我们都会尽力回答的。</p>", "created": "2015-07-29T03:23:01Z", "bucket_order": 247, "bucket_name": "Week 7/26 - 8/1", "type": "feedback", "tag_good": [], "uid": "hdjonbiyfs62ie", "children": [], "tag_good_arr": [], "id": "ico7j5o56nq361", "updated": "2015-07-29T03:23:01Z", "config": {}}], "tag_good_arr": [], "no_answer": 0, "id": "icnmgu82lrr33e", "updated": "2015-07-28T17:33:21Z", "config": {}}], "tag_good_arr": [], "id": "icla23cwgp91ht", "config": {}, "status": "active", "drafts": null, "request_instructor": 0, "request_instructor_me": false, "bookmarked": 4, "num_favorites": 0, "my_favorite": false, "is_bookmarked": false, "is_tag_good": false, "q_edits": [], "i_edits": [], "s_edits": [], "t": 1643167887602, "default_anonymity": "no"}, "error": null, "aid": "kyuzqghefkt31c"}