{"result": {"folders": ["lecture15", "q&amp;a", "通知"], "nr": 809, "data": {"embed_links": []}, "created": "2016-04-18T01:43:11Z", "bucket_order": 3, "no_answer_followup": 0, "change_log": [{"uid": "hdjonbiyfs62ie", "anon": "no", "when": "2016-04-18T01:43:11Z", "data": "in5c7nqybot48q", "type": "create"}, {"to": "in5c7nqwnhb48p", "uid": "i0nuu5yhgno5tv", "anon": "no", "when": "2016-04-18T01:45:00Z", "type": "followup"}, {"to": "in5c7nqwnhb48p", "uid": "i242q8ug7vw40x", "anon": "no", "when": "2016-04-18T01:45:15Z", "type": "followup"}, {"to": "in5c7nqwnhb48p", "uid": "i0zaci5voig5h", "anon": "no", "when": "2016-04-18T01:54:03Z", "type": "followup"}, {"to": "in5c7nqwnhb48p", "anon": "full", "when": "2016-04-18T01:58:24Z", "type": "feedback", "uid_a": "a_0"}, {"to": "in5c7nqwnhb48p", "uid": "i0brpl1lbyui6", "anon": "no", "when": "2016-04-18T02:02:09Z", "type": "followup"}, {"to": "in5c7nqwnhb48p", "uid": "i1569mw0xp954u", "anon": "no", "when": "2016-04-18T02:05:25Z", "type": "followup"}, {"to": "in5c7nqwnhb48p", "uid": "i21zpwab2z775p", "anon": "no", "when": "2016-04-18T02:06:11Z", "type": "followup"}, {"to": "in5c7nqwnhb48p", "uid": "i0f24oie8102cr", "anon": "no", "when": "2016-04-18T02:12:25Z", "type": "followup"}, {"to": "in5c7nqwnhb48p", "uid": "i3qk2vs65x276j", "anon": "no", "when": "2016-04-18T02:56:47Z", "type": "followup"}, {"to": "in5c7nqwnhb48p", "uid": "i0gl5kctugw3xi", "anon": "no", "when": "2016-04-18T03:38:30Z", "type": "followup"}, {"to": "in5c7nqwnhb48p", "uid": "i0yuo4o74sx70w", "anon": "no", "when": "2016-04-18T03:53:04Z", "type": "followup"}, {"to": "in5c7nqwnhb48p", "uid": "i0c9nvk0xzc2n3", "anon": "no", "when": "2016-04-18T05:34:30Z", "type": "followup"}, {"to": "in5c7nqwnhb48p", "uid": "im4yagyfl3chl", "anon": "no", "when": "2016-04-18T06:56:03Z", "type": "followup"}, {"to": "in5c7nqwnhb48p", "uid": "hdjonbiyfs62ie", "anon": "no", "when": "2016-04-18T15:13:02Z", "type": "feedback"}, {"to": "in5c7nqwnhb48p", "uid": "ie7xy71bn7b1s2", "anon": "no", "when": "2016-04-19T08:17:57Z", "type": "followup"}, {"to": "in5c7nqwnhb48p", "uid": "ikvcvr6di5i7ma", "anon": "no", "when": "2016-04-19T14:43:11Z", "type": "followup"}], "bucket_name": "Today", "history": [{"anon": "no", "uid": "hdjonbiyfs62ie", "subject": "操作系统课第15讲课堂签到", "created": "2016-04-18T01:43:11Z", "content": "<p>今天上课只来了15个同学&#xff0c;我只好在这里签到了。</p>\n<p></p>\n<p>请来上课的同学&#xff0c;回复自己的学号和姓名。</p>"}], "type": "note", "tags": ["instructor-note", "lecture15", "q&amp;a", "通知"], "tag_good": [], "unique_views": 157, "children": [{"anon": "no", "folders": [], "data": {"embed_links": null}, "no_upvotes": 0, "subject": "<p>钱迪晨 2013011402</p>", "created": "2016-04-18T01:45:00Z", "bucket_order": 212, "bucket_name": "Week 4/17 - 4/23", "type": "followup", "tag_good": [], "uid": "i0nuu5yhgno5tv", "children": [], "tag_good_arr": [], "no_answer": 0, "id": "in5ca05lr296oo", "updated": "2016-04-18T01:45:00Z", "config": {}}, {"anon": "no", "folders": [], "data": {"embed_links": null}, "no_upvotes": 0, "subject": "<p></p>\n<p>2013011356 董豪宇</p>", "created": "2016-04-18T01:45:15Z", "bucket_order": 212, "bucket_name": "Week 4/17 - 4/23", "type": "followup", "tag_good": [], "uid": "i242q8ug7vw40x", "children": [], "tag_good_arr": [], "no_answer": 0, "id": "in5cabll4xx52j", "updated": "2016-04-18T01:45:15Z", "config": {}}, {"anon": "no", "folders": [], "data": {"embed_links": null}, "no_upvotes": 0, "subject": "<p>朱新瑞 2013011411</p>\n<p>最后第二排靠门第二个</p>", "created": "2016-04-18T01:54:03Z", "bucket_order": 212, "bucket_name": "Week 4/17 - 4/23", "type": "followup", "tag_good": [], "uid": "i0zaci5voig5h", "children": [{"anon": "full", "folders": [], "data": {"embed_links": null}, "subject": "<p></p><pre>(&#xffe3;▽&#xffe3;)</pre>", "created": "2016-04-18T01:58:24Z", "bucket_order": 212, "bucket_name": "Week 4/17 - 4/23", "type": "feedback", "tag_good": [], "uid_a": "a_0", "children": [], "tag_good_arr": [], "id": "in5cr8oec3zu9", "updated": "2016-04-18T01:58:24Z", "config": {}}], "tag_good_arr": [], "no_answer": 0, "id": "in5cln8k5h3586", "updated": "2016-04-18T01:54:03Z", "config": {}}, {"anon": "no", "folders": [], "data": {"embed_links": null}, "no_upvotes": 0, "subject": "<p>杨明 2013011412</p>", "created": "2016-04-18T02:02:09Z", "bucket_order": 212, "bucket_name": "Week 4/17 - 4/23", "type": "followup", "tag_good": [], "uid": "i0brpl1lbyui6", "children": [], "tag_good_arr": [], "no_answer": 0, "id": "in5cw2ine3e4iv", "updated": "2016-04-18T02:02:09Z", "config": {}}, {"anon": "no", "folders": [], "data": {"embed_links": null}, "no_upvotes": 0, "subject": "<p>程凯 2013011303</p>", "created": "2016-04-18T02:05:25Z", "bucket_order": 212, "bucket_name": "Week 4/17 - 4/23", "type": "followup", "tag_good": [], "uid": "i1569mw0xp954u", "children": [], "tag_good_arr": [], "no_answer": 0, "id": "in5d09gljwp5mu", "updated": "2016-04-18T02:05:25Z", "config": {}}, {"anon": "no", "folders": [], "data": {"embed_links": null}, "no_upvotes": 0, "subject": "<p>马志明 2013011395</p>", "created": "2016-04-18T02:06:11Z", "bucket_order": 212, "bucket_name": "Week 4/17 - 4/23", "type": "followup", "tag_good": [], "uid": "i21zpwab2z775p", "children": [], "tag_good_arr": [], "no_answer": 0, "id": "in5d1990l2r7lw", "updated": "2016-04-18T02:06:11Z", "config": {}}, {"anon": "no", "folders": [], "data": {"embed_links": null}, "no_upvotes": 0, "subject": "<p>叶子鹏 2013011404</p>", "created": "2016-04-18T02:12:25Z", "bucket_order": 212, "bucket_name": "Week 4/17 - 4/23", "type": "followup", "tag_good": [], "uid": "i0f24oie8102cr", "children": [], "tag_good_arr": [], "no_answer": 0, "id": "in5d99c3s8253q", "updated": "2016-04-18T02:12:25Z", "config": {}}, {"anon": "no", "folders": [], "data": {"embed_links": null}, "no_upvotes": 0, "subject": "<p></p>\n<p>贺子松 2013011296</p>", "created": "2016-04-18T02:56:47Z", "bucket_order": 212, "bucket_name": "Week 4/17 - 4/23", "type": "followup", "tag_good": [], "uid": "i3qk2vs65x276j", "children": [], "tag_good_arr": [], "no_answer": 0, "id": "in5eubh5g2ywm", "updated": "2016-04-18T02:56:47Z", "config": {}}, {"anon": "no", "folders": [], "data": {"embed_links": null}, "no_upvotes": 0, "subject": "<p>高思达 2013011413</p>", "created": "2016-04-18T03:38:30Z", "bucket_order": 212, "bucket_name": "Week 4/17 - 4/23", "type": "followup", "tag_good": [], "uid": "i0gl5kctugw3xi", "children": [], "tag_good_arr": [], "no_answer": 0, "id": "in5gbymtlqkey", "updated": "2016-04-18T03:38:30Z", "config": {}}, {"anon": "no", "folders": [], "data": {"embed_links": null}, "no_upvotes": 0, "subject": "<p>张浩天 2013011416</p>", "created": "2016-04-18T03:53:04Z", "bucket_order": 212, "bucket_name": "Week 4/17 - 4/23", "type": "followup", "tag_good": [], "uid": "i0yuo4o74sx70w", "children": [], "tag_good_arr": [], "no_answer": 0, "id": "in5gupe7lqx4tw", "updated": "2016-04-18T03:53:04Z", "config": {}}, {"anon": "no", "folders": [], "data": {"embed_links": null}, "no_upvotes": 0, "subject": "<p>姚炫容 2013011379</p>", "created": "2016-04-18T05:34:30Z", "bucket_order": 212, "bucket_name": "Week 4/17 - 4/23", "type": "followup", "tag_good": [], "uid": "i0c9nvk0xzc2n3", "children": [], "tag_good_arr": [], "no_answer": 0, "id": "in5kh4yrrjh346", "updated": "2016-04-18T05:34:30Z", "config": {}}, {"anon": "no", "folders": [], "data": {"embed_links": null}, "no_upvotes": 0, "subject": "<p>最后排右边</p>", "created": "2016-04-18T06:56:03Z", "bucket_order": 212, "bucket_name": "Week 4/17 - 4/23", "type": "followup", "tag_good": [], "uid": "im4yagyfl3chl", "children": [{"anon": "no", "folders": [], "data": {"embed_links": null}, "subject": "<p>到这里有12个人了。谢谢各位同学的回复。</p>", "created": "2016-04-18T15:13:02Z", "bucket_order": 212, "bucket_name": "Week 4/17 - 4/23", "type": "feedback", "tag_good": [], "uid": "hdjonbiyfs62ie", "children": [], "tag_good_arr": [], "id": "in6555dr1306u3", "updated": "2016-04-18T15:13:02Z", "config": {}}], "tag_good_arr": [], "no_answer": 0, "id": "in5ne0meyyb5zs", "updated": "2016-04-18T06:56:03Z", "config": {}}, {"anon": "no", "folders": [], "data": {"embed_links": null}, "no_upvotes": 0, "subject": "<p>郭嘉丞 2013011509 靠着中间的门</p>", "created": "2016-04-19T08:17:57Z", "bucket_order": 212, "bucket_name": "Week 4/17 - 4/23", "type": "followup", "tag_good": [], "uid": "ie7xy71bn7b1s2", "children": [], "tag_good_arr": [], "no_answer": 0, "id": "in75r6r863p27a", "updated": "2016-04-19T08:17:57Z", "config": {}}, {"anon": "no", "folders": [], "data": {"embed_links": null}, "no_upvotes": 0, "subject": "<p>谢琛睿 2013011406</p>", "created": "2016-04-19T14:43:11Z", "bucket_order": 212, "bucket_name": "Week 4/17 - 4/23", "type": "followup", "tag_good": [], "uid": "ikvcvr6di5i7ma", "children": [], "tag_good_arr": [], "no_answer": 0, "id": "in7jilrltjf26h", "updated": "2016-04-19T14:43:11Z", "config": {}}], "tag_good_arr": [], "id": "in5c7nqwnhb48p", "config": {}, "status": "active", "drafts": null, "request_instructor": 0, "request_instructor_me": false, "bookmarked": 18, "num_favorites": 0, "my_favorite": false, "is_bookmarked": false, "is_tag_good": false, "q_edits": [], "i_edits": [], "s_edits": [], "t": 1643168562524, "default_anonymity": "no"}, "error": null, "aid": "kyv04x986dykq"}